qsv/__init__.py
qsv/py.typed
qsv/controllers/CsvController.py
qsv/controllers/DataFrameController.py
qsv/controllers/LogController.py
qsv/controllers/QuiltController.py
qsv/controllers/YamlController.py
qsv/operations/chainables/__init__.py
qsv/operations/chainables/changetz.py
qsv/operations/chainables/contains.py
qsv/operations/chainables/count.py
qsv/operations/chainables/grep.py
qsv/operations/chainables/head.py
qsv/operations/chainables/isin.py
qsv/operations/chainables/renamecol.py
qsv/operations/chainables/sed.py
qsv/operations/chainables/select.py
qsv/operations/chainables/sort.py
qsv/operations/chainables/tail.py
qsv/operations/chainables/uniq.py
qsv/operations/finalizers/__init__.py
qsv/operations/finalizers/dump.py
qsv/operations/finalizers/headers.py
qsv/operations/finalizers/show.py
qsv/operations/finalizers/showquery.py
qsv/operations/finalizers/showtable.py
qsv/operations/finalizers/stats.py
qsv/operations/initializers/__init__.py
qsv/operations/initializers/load.py
qsv/operations/quilters/__init__.py
qsv/operations/quilters/quilt.py
qsv/operations/quilters/quilt_visualize.py
qsv/utils/DataFrameUtils.py
qsv/utils/FileUtils.py
qsv/views/TableView.py
qsv-0.4.2.dist-info/METADATA
qsv-0.4.2.dist-info/WHEEL
qsv-0.4.2.dist-info/entry_points.txt
qsv-0.4.2.dist-info/licenses/LICENSE
qsv-0.4.2.dist-info/RECORD
