Metadata-Version: 2.4
Name: qsv
Version: 0.4.2
Summary: A tool that provides elastic and rapid filtering for efficient analysis of huge CSV files, such as eventlogs.
Author-email: sumeshi <sum3sh1@protonmail.com>
License-File: LICENSE
Requires-Python: >=3.11
Requires-Dist: fire>=0.7.0
Requires-Dist: polars>=1.17.1
Requires-Dist: pyyaml>=6.0.2
Requires-Dist: rich>=13.9.4
